cmdfunctools/__init__.py
cmdfunctools/__version__.py
cmdfunctools/decorators.py
cmdfunctools/exceptions.py
cmdfunctools/types.py
cmdfunctools-0.0.3.dist-info/LICENSE.txt
cmdfunctools-0.0.3.dist-info/METADATA
cmdfunctools-0.0.3.dist-info/WHEEL
cmdfunctools-0.0.3.dist-info/top_level.txt
cmdfunctools-0.0.3.dist-info/RECORD
