Metadata-Version: 2.1
Name: cmdfunctools
Version: 0.0.3
Summary: make python functions usable from command line
Home-page: http://pypi.python.org/pypi/cmdfunctions
Author: Mr-Io
Author-email: macrigaud@gmail.com
License: UNKNOWN
Platform: UNKNOWN
Classifier: Development Status :: 3 - Alpha
Classifier: Intended Audience :: Developers
Classifier: Natural Language :: English
Classifier: License :: OSI Approved :: MIT License
Classifier: Programming Language :: Python
Classifier: Programming Language :: Python :: 3
Classifier: Programming Language :: Python :: 3.7
Classifier: Programming Language :: Python :: Implementation :: CPython
Classifier: Programming Language :: Python :: Implementation :: PyPy
Requires-Python: >=3.7, <4
